[
  {
    "id": 0,
    "new_candidate": true,
    "communication_updates": false,
    "hiring_stage": true,
    "resume_status": false,
    "events_update": true,
    "recruitment_dates": false,
    "security_alerts": true,
    "renewal_dates": false,
    "recruiter_id": 1
  },
  {
    "id": 1,
    "new_candidate": true,
    "communication_updates": false,
    "hiring_stage": true,
    "resume_status": false,
    "events_update": true,
    "recruitment_dates": false,
    "security_alerts": true,
    "renewal_dates": false,
    "recruiter_id": 2
  },
  {
    "id": 2,
    "new_candidate": true,
    "communication_updates": false,
    "hiring_stage": true,
    "resume_status": false,
    "events_update": true,
    "recruitment_dates": false,
    "security_alerts": true,
    "renewal_dates": false,
    "recruiter_id": 3
  },
  {
    "id": 3,
    "new_candidate": true,
    "communication_updates": false,
    "hiring_stage": true,
    "resume_status": false,
    "events_update": true,
    "recruitment_dates": false,
    "security_alerts": true,
    "renewal_dates": false,
    "recruiter_id": 4
  },
  {
    "id": 4,
    "new_candidate": true,
    "communication_updates": false,
    "hiring_stage": true,
    "resume_status": false,
    "events_update": true,
    "recruitment_dates": false,
    "security_alerts": true,
    "renewal_dates": false,
    "recruiter_id": 5
  },
  {
    "id": 5,
    "new_candidate": true,
    "communication_updates": false,
    "hiring_stage": true,
    "resume_status": false,
    "events_update": true,
    "recruitment_dates": false,
    "security_alerts": true,
    "renewal_dates": false,
    "recruiter_id": 6
  },
  {
    "id": 6,
    "new_candidate": true,
    "communication_updates": false,
    "hiring_stage": true,
    "resume_status": false,
    "events_update": true,
    "recruitment_dates": false,
    "security_alerts": true,
    "renewal_dates": false,
    "recruiter_id": 7
  },
  {
    "id": 7,
    "new_candidate": true,
    "communication_updates": false,
    "hiring_stage": true,
    "resume_status": false,
    "events_update": true,
    "recruitment_dates": false,
    "security_alerts": true,
    "renewal_dates": false,
    "recruiter_id": 8
  },
  {
    "id": 8,
    "new_candidate": true,
    "communication_updates": false,
    "hiring_stage": true,
    "resume_status": false,
    "events_update": true,
    "recruitment_dates": false,
    "security_alerts": true,
    "renewal_dates": false,
    "recruiter_id": 9
  },
  {
    "id": 9,
    "new_candidate": true,
    "communication_updates": false,
    "hiring_stage": true,
    "resume_status": false,
    "events_update": true,
    "recruitment_dates": false,
    "security_alerts": true,
    "renewal_dates": false,
    "recruiter_id": 10
  },
  {
    "id": 10,
    "new_candidate": true,
    "communication_updates": false,
    "hiring_stage": true,
    "resume_status": false,
    "events_update": true,
    "recruitment_dates": false,
    "security_alerts": true,
    "renewal_dates": false,
    "recruiter_id": 11
  },
  {
    "id": 11,
    "new_candidate": true,
    "communication_updates": false,
    "hiring_stage": true,
    "resume_status": false,
    "events_update": true,
    "recruitment_dates": false,
    "security_alerts": true,
    "renewal_dates": false,
    "recruiter_id": 12
  },
  {
    "id": 12,
    "new_candidate": true,
    "communication_updates": false,
    "hiring_stage": true,
    "resume_status": false,
    "events_update": true,
    "recruitment_dates": false,
    "security_alerts": true,
    "renewal_dates": false,
    "recruiter_id": 13
  },
  {
    "id": 13,
    "new_candidate": true,
    "communication_updates": false,
    "hiring_stage": true,
    "resume_status": false,
    "events_update": true,
    "recruitment_dates": false,
    "security_alerts": true,
    "renewal_dates": false,
    "recruiter_id": 14
  },
  {
    "id": 14,
    "new_candidate": true,
    "communication_updates": false,
    "hiring_stage": true,
    "resume_status": false,
    "events_update": true,
    "recruitment_dates": false,
    "security_alerts": true,
    "renewal_dates": false,
    "recruiter_id": 15
  },
  {
    "id": 15,
    "new_candidate": true,
    "communication_updates": false,
    "hiring_stage": true,
    "resume_status": false,
    "events_update": true,
    "recruitment_dates": false,
    "security_alerts": true,
    "renewal_dates": false,
    "recruiter_id": 16
  },
  {
    "id": 16,
    "new_candidate": true,
    "communication_updates": false,
    "hiring_stage": true,
    "resume_status": false,
    "events_update": true,
    "recruitment_dates": false,
    "security_alerts": true,
    "renewal_dates": false,
    "recruiter_id": 17
  },
  {
    "id": 17,
    "new_candidate": true,
    "communication_updates": false,
    "hiring_stage": true,
    "resume_status": false,
    "events_update": true,
    "recruitment_dates": false,
    "security_alerts": true,
    "renewal_dates": false,
    "recruiter_id": 18
  },
  {
    "id": 18,
    "new_candidate": true,
    "communication_updates": false,
    "hiring_stage": true,
    "resume_status": false,
    "events_update": true,
    "recruitment_dates": false,
    "security_alerts": true,
    "renewal_dates": false,
    "recruiter_id": 19
  },
  {
    "id": 19,
    "new_candidate": true,
    "communication_updates": false,
    "hiring_stage": true,
    "resume_status": false,
    "events_update": true,
    "recruitment_dates": false,
    "security_alerts": true,
    "renewal_dates": false,
    "recruiter_id": 20
  },
  {
    "id": 20,
    "new_candidate": true,
    "communication_updates": false,
    "hiring_stage": true,
    "resume_status": false,
    "events_update": true,
    "recruitment_dates": false,
    "security_alerts": true,
    "renewal_dates": false,
    "recruiter_id": 21
  },
  {
    "id": 21,
    "new_candidate": true,
    "communication_updates": false,
    "hiring_stage": true,
    "resume_status": false,
    "events_update": true,
    "recruitment_dates": false,
    "security_alerts": true,
    "renewal_dates": false,
    "recruiter_id": 22
  },
  {
    "id": 22,
    "new_candidate": true,
    "communication_updates": false,
    "hiring_stage": true,
    "resume_status": false,
    "events_update": true,
    "recruitment_dates": false,
    "security_alerts": true,
    "renewal_dates": false,
    "recruiter_id": 23
  },
  {
    "id": 23,
    "new_candidate": true,
    "communication_updates": false,
    "hiring_stage": true,
    "resume_status": false,
    "events_update": true,
    "recruitment_dates": false,
    "security_alerts": true,
    "renewal_dates": false,
    "recruiter_id": 24
  },
  {
    "id": 24,
    "new_candidate": true,
    "communication_updates": false,
    "hiring_stage": true,
    "resume_status": false,
    "events_update": true,
    "recruitment_dates": false,
    "security_alerts": true,
    "renewal_dates": false,
    "recruiter_id": 25
  },
  {
    "id": 25,
    "new_candidate": true,
    "communication_updates": false,
    "hiring_stage": true,
    "resume_status": false,
    "events_update": true,
    "recruitment_dates": false,
    "security_alerts": true,
    "renewal_dates": false,
    "recruiter_id": 26
  },
  {
    "id": 26,
    "new_candidate": true,
    "communication_updates": false,
    "hiring_stage": true,
    "resume_status": false,
    "events_update": true,
    "recruitment_dates": false,
    "security_alerts": true,
    "renewal_dates": false,
    "recruiter_id": 27
  },
  {
    "id": 27,
    "new_candidate": true,
    "communication_updates": false,
    "hiring_stage": true,
    "resume_status": false,
    "events_update": true,
    "recruitment_dates": false,
    "security_alerts": true,
    "renewal_dates": false,
    "recruiter_id": 28
  },
  {
    "id": 28,
    "new_candidate": true,
    "communication_updates": false,
    "hiring_stage": true,
    "resume_status": false,
    "events_update": true,
    "recruitment_dates": false,
    "security_alerts": true,
    "renewal_dates": false,
    "recruiter_id": 29
  },
  {
    "id": 29,
    "new_candidate": true,
    "communication_updates": false,
    "hiring_stage": true,
    "resume_status": false,
    "events_update": true,
    "recruitment_dates": false,
    "security_alerts": true,
    "renewal_dates": false,
    "recruiter_id": 30
  },
  {
    "id": 30,
    "new_candidate": true,
    "communication_updates": false,
    "hiring_stage": true,
    "resume_status": false,
    "events_update": true,
    "recruitment_dates": false,
    "security_alerts": true,
    "renewal_dates": false,
    "recruiter_id": 31
  },
  {
    "id": 31,
    "new_candidate": true,
    "communication_updates": false,
    "hiring_stage": true,
    "resume_status": false,
    "events_update": true,
    "recruitment_dates": false,
    "security_alerts": true,
    "renewal_dates": false,
    "recruiter_id": 32
  },
  {
    "id": 32,
    "new_candidate": true,
    "communication_updates": false,
    "hiring_stage": true,
    "resume_status": false,
    "events_update": true,
    "recruitment_dates": false,
    "security_alerts": true,
    "renewal_dates": false,
    "recruiter_id": 33
  },
  {
    "id": 33,
    "new_candidate": true,
    "communication_updates": false,
    "hiring_stage": true,
    "resume_status": false,
    "events_update": true,
    "recruitment_dates": false,
    "security_alerts": true,
    "renewal_dates": false,
    "recruiter_id": 34
  },
  {
    "id": 34,
    "new_candidate": true,
    "communication_updates": false,
    "hiring_stage": true,
    "resume_status": false,
    "events_update": true,
    "recruitment_dates": false,
    "security_alerts": true,
    "renewal_dates": false,
    "recruiter_id": 35
  },
  {
    "id": 35,
    "new_candidate": true,
    "communication_updates": false,
    "hiring_stage": true,
    "resume_status": false,
    "events_update": true,
    "recruitment_dates": false,
    "security_alerts": true,
    "renewal_dates": false,
    "recruiter_id": 36
  },
  {
    "id": 36,
    "new_candidate": true,
    "communication_updates": false,
    "hiring_stage": true,
    "resume_status": false,
    "events_update": true,
    "recruitment_dates": false,
    "security_alerts": true,
    "renewal_dates": false,
    "recruiter_id": 37
  },
  {
    "id": 37,
    "new_candidate": true,
    "communication_updates": false,
    "hiring_stage": true,
    "resume_status": false,
    "events_update": true,
    "recruitment_dates": false,
    "security_alerts": true,
    "renewal_dates": false,
    "recruiter_id": 38
  },
  {
    "id": 38,
    "new_candidate": true,
    "communication_updates": false,
    "hiring_stage": true,
    "resume_status": false,
    "events_update": true,
    "recruitment_dates": false,
    "security_alerts": true,
    "renewal_dates": false,
    "recruiter_id": 39
  },
  {
    "id": 39,
    "new_candidate": true,
    "communication_updates": false,
    "hiring_stage": true,
    "resume_status": false,
    "events_update": true,
    "recruitment_dates": false,
    "security_alerts": true,
    "renewal_dates": false,
    "recruiter_id": 40
  },
  {
    "id": 40,
    "new_candidate": true,
    "communication_updates": false,
    "hiring_stage": true,
    "resume_status": false,
    "events_update": true,
    "recruitment_dates": false,
    "security_alerts": true,
    "renewal_dates": false,
    "recruiter_id": 41
  },
  {
    "id": 41,
    "new_candidate": true,
    "communication_updates": false,
    "hiring_stage": true,
    "resume_status": false,
    "events_update": true,
    "recruitment_dates": false,
    "security_alerts": true,
    "renewal_dates": false,
    "recruiter_id": 42
  },
  {
    "id": 42,
    "new_candidate": true,
    "communication_updates": false,
    "hiring_stage": true,
    "resume_status": false,
    "events_update": true,
    "recruitment_dates": false,
    "security_alerts": true,
    "renewal_dates": false,
    "recruiter_id": 43
  },
  {
    "id": 43,
    "new_candidate": true,
    "communication_updates": false,
    "hiring_stage": true,
    "resume_status": false,
    "events_update": true,
    "recruitment_dates": false,
    "security_alerts": true,
    "renewal_dates": false,
    "recruiter_id": 44
  },
  {
    "id": 44,
    "new_candidate": true,
    "communication_updates": false,
    "hiring_stage": true,
    "resume_status": false,
    "events_update": true,
    "recruitment_dates": false,
    "security_alerts": true,
    "renewal_dates": false,
    "recruiter_id": 45
  },
  {
    "id": 45,
    "new_candidate": true,
    "communication_updates": false,
    "hiring_stage": true,
    "resume_status": false,
    "events_update": true,
    "recruitment_dates": false,
    "security_alerts": true,
    "renewal_dates": false,
    "recruiter_id": 46
  },
  {
    "id": 46,
    "new_candidate": true,
    "communication_updates": false,
    "hiring_stage": true,
    "resume_status": false,
    "events_update": true,
    "recruitment_dates": false,
    "security_alerts": true,
    "renewal_dates": false,
    "recruiter_id": 47
  },
  {
    "id": 47,
    "new_candidate": true,
    "communication_updates": false,
    "hiring_stage": true,
    "resume_status": false,
    "events_update": true,
    "recruitment_dates": false,
    "security_alerts": true,
    "renewal_dates": false,
    "recruiter_id": 48
  },
  {
    "id": 48,
    "new_candidate": true,
    "communication_updates": false,
    "hiring_stage": true,
    "resume_status": false,
    "events_update": true,
    "recruitment_dates": false,
    "security_alerts": true,
    "renewal_dates": false,
    "recruiter_id": 49
  },
  {
    "id": 49,
    "new_candidate": true,
    "communication_updates": false,
    "hiring_stage": true,
    "resume_status": false,
    "events_update": true,
    "recruitment_dates": false,
    "security_alerts": true,
    "renewal_dates": false,
    "recruiter_id": 50
  },
  {
    "id": 50,
    "new_candidate": true,
    "communication_updates": false,
    "hiring_stage": true,
    "resume_status": false,
    "events_update": true,
    "recruitment_dates": false,
    "security_alerts": true,
    "renewal_dates": false,
    "recruiter_id": 51
  },
  {
    "id": 51,
    "new_candidate": true,
    "communication_updates": false,
    "hiring_stage": true,
    "resume_status": false,
    "events_update": true,
    "recruitment_dates": false,
    "security_alerts": true,
    "renewal_dates": false,
    "recruiter_id": 52
  },
  {
    "id": 52,
    "new_candidate": true,
    "communication_updates": false,
    "hiring_stage": true,
    "resume_status": false,
    "events_update": true,
    "recruitment_dates": false,
    "security_alerts": true,
    "renewal_dates": false,
    "recruiter_id": 53
  },
  {
    "id": 53,
    "new_candidate": true,
    "communication_updates": false,
    "hiring_stage": true,
    "resume_status": false,
    "events_update": true,
    "recruitment_dates": false,
    "security_alerts": true,
    "renewal_dates": false,
    "recruiter_id": 54
  },
  {
    "id": 54,
    "new_candidate": true,
    "communication_updates": false,
    "hiring_stage": true,
    "resume_status": false,
    "events_update": true,
    "recruitment_dates": false,
    "security_alerts": true,
    "renewal_dates": false,
    "recruiter_id": 55
  },
  {
    "id": 55,
    "new_candidate": true,
    "communication_updates": false,
    "hiring_stage": true,
    "resume_status": false,
    "events_update": true,
    "recruitment_dates": false,
    "security_alerts": true,
    "renewal_dates": false,
    "recruiter_id": 56
  },
  {
    "id": 56,
    "new_candidate": true,
    "communication_updates": false,
    "hiring_stage": true,
    "resume_status": false,
    "events_update": true,
    "recruitment_dates": false,
    "security_alerts": true,
    "renewal_dates": false,
    "recruiter_id": 57
  },
  {
    "id": 57,
    "new_candidate": true,
    "communication_updates": false,
    "hiring_stage": true,
    "resume_status": false,
    "events_update": true,
    "recruitment_dates": false,
    "security_alerts": true,
    "renewal_dates": false,
    "recruiter_id": 58
  },
  {
    "id": 58,
    "new_candidate": true,
    "communication_updates": false,
    "hiring_stage": true,
    "resume_status": false,
    "events_update": true,
    "recruitment_dates": false,
    "security_alerts": true,
    "renewal_dates": false,
    "recruiter_id": 59
  },
  {
    "id": 59,
    "new_candidate": true,
    "communication_updates": false,
    "hiring_stage": true,
    "resume_status": false,
    "events_update": true,
    "recruitment_dates": false,
    "security_alerts": true,
    "renewal_dates": false,
    "recruiter_id": 60
  },
  {
    "id": 60,
    "new_candidate": true,
    "communication_updates": false,
    "hiring_stage": true,
    "resume_status": false,
    "events_update": true,
    "recruitment_dates": false,
    "security_alerts": true,
    "renewal_dates": false,
    "recruiter_id": 61
  },
  {
    "id": 61,
    "new_candidate": true,
    "communication_updates": false,
    "hiring_stage": true,
    "resume_status": false,
    "events_update": true,
    "recruitment_dates": false,
    "security_alerts": true,
    "renewal_dates": false,
    "recruiter_id": 62
  }
]